magpy/__init__.py
magpy/estimation/__init__.py
magpy/estimation/categorical.py
magpy/estimation/double.py
magpy/estimation/effects.py
magpy/logger/__init__.py
magpy/logger/base.py
magpy/oracles/__init__.py
magpy/oracles/kernel.py
magpy/oracles/mixed.py
magpy/oracles/oracles.py
magpy/search/__init__.py
magpy/search/astar.py
magpy/search/orientation.py
magpy/search/pcskeleton.py
magpy/utils/DataManager.py
magpy/utils/__init__.py
causal_magpy-0.1.1.dist-info/METADATA
causal_magpy-0.1.1.dist-info/WHEEL
causal_magpy-0.1.1.dist-info/top_level.txt
causal_magpy-0.1.1.dist-info/RECORD
