Metadata-Version: 2.1
Name: causal-magpy
Version: 0.1.1
Summary: A package for causal discovery and causal inference algorithms
Home-page: https://github.com/ergodic-ai/magpy
Author: ergodic.ai
Author-email: Andre <andre@ergodic.ai>
Project-URL: Homepage, https://github.com/ergodic-ai/magpy
Classifier: Programming Language :: Python :: 3
Classifier: License :: OSI Approved :: MIT License
Classifier: Operating System :: OS Independent
Requires-Python: >=3.6
Requires-Dist: joblib
Requires-Dist: networkx
Requires-Dist: numpy
Requires-Dist: pandas
Requires-Dist: pydantic
Requires-Dist: scikit-learn
Requires-Dist: pytest
Requires-Dist: matplotlib
Requires-Dist: tqdm
Requires-Dist: causal-learn
Requires-Dist: causalml
